q2_metabodisttrees/__init__.py
q2_metabodisttrees/_metabodisttrees.py
q2_metabodisttrees/citations.bib
q2_metabodisttrees/plugin_setup.py
q2_metabodisttrees/data/ChemOnt_2_1.obo
q2_metabodisttrees/data/citations.bib
q2_metabodisttrees-0.0.13.dist-info/LICENSE
q2_metabodisttrees-0.0.13.dist-info/METADATA
q2_metabodisttrees-0.0.13.dist-info/WHEEL
q2_metabodisttrees-0.0.13.dist-info/entry_points.txt
q2_metabodisttrees-0.0.13.dist-info/top_level.txt
q2_metabodisttrees-0.0.13.dist-info/RECORD
