Metadata-Version: 2.1
Name: q2-metabodisttrees
Version: 0.0.13
Summary: Chemically-informed trees based on substructure or chemical class information.
Home-page: https://github.com/madeleineernst/MetaboDistTrees
Author: Madeleine Ernst
Author-email: ernst.made@gmail.com
License: BSD-3-Clause
Platform: UNKNOWN
